boxs/__init__.py
boxs/api.py
boxs/box.py
boxs/box_registry.py
boxs/checksum.py
boxs/cli.py
boxs/config.py
boxs/data.py
boxs/errors.py
boxs/filesystem.py
boxs/graph.py
boxs/io.py
boxs/origin.py
boxs/pandas.py
boxs/run.py
boxs/statistics.py
boxs/storage.py
boxs/tensorflow.py
boxs/transform.py
boxs/value_types.py
boxs-0.1.dist-info/entry_points.txt
boxs-0.1.dist-info/LICENSE
boxs-0.1.dist-info/WHEEL
boxs-0.1.dist-info/METADATA
boxs-0.1.dist-info/RECORD
