Metadata-Version: 2.1
Name: boxs
Version: 0.1
Summary: Automatically track data and artifacts
Keywords: machine learning,data,lineage,tracking,track,tracker,history,source,artifact,data science,graph,dependency,dependencies
Author-email: Christoph Emonds <chris+git@kant.ai>
Requires-Python: >=3.6
Classifier: Intended Audience :: Developers
Classifier: Intended Audience :: Information Technology
Classifier: Intended Audience :: Science/Research
Classifier: License :: OSI Approved :: MIT License
Classifier: Programming Language :: Python :: 3
Classifier: Topic :: Software Development :: Libraries :: Python Modules
Classifier: Topic :: Scientific/Engineering
Classifier: Topic :: Scientific/Engineering :: Artificial Intelligence
Classifier: Topic :: Scientific/Engineering :: Information Analysis
Classifier: Topic :: Security
Classifier: Topic :: Security :: Cryptography
Classifier: Topic :: System :: Archiving
Classifier: Topic :: System :: Distributed Computing
Classifier: Topic :: System :: Filesystems
Requires-Dist: tox ; extra == "docs"
Requires-Dist: pandas ; extra == "pandas"
Requires-Dist: flit ; extra == "release"
Requires-Dist: tox ; extra == "test"
Project-URL: Documentation, https://docs.kant.ai/boxs/latest/
Project-URL: Source, https://gitlab.com/kantai/boxs/
Provides-Extra: docs
Provides-Extra: pandas
Provides-Extra: release
Provides-Extra: test
